.testr.conf
AUTHORS
ChangeLog
LICENSE
MANIFEST.in
README.rst
docs-requirements.txt
requirements.txt
setup.cfg
setup.py
test-requirements.txt
tox.ini
doc/Makefile
doc/source/builders.rst
doc/source/conf.py
doc/source/definition.rst
doc/source/execution.rst
doc/source/extending.rst
doc/source/hipchat.rst
doc/source/index.rst
doc/source/installation.rst
doc/source/metadata.rst
doc/source/notifications.rst
doc/source/parameters.rst
doc/source/project_externaljob.rst
doc/source/project_flow.rst
doc/source/project_freestyle.rst
doc/source/project_matrix.rst
doc/source/project_maven.rst
doc/source/project_multijob.rst
doc/source/project_pipeline.rst
doc/source/project_workflow.rst
doc/source/properties.rst
doc/source/publishers.rst
doc/source/quick-start.rst
doc/source/reporters.rst
doc/source/scm.rst
doc/source/triggers.rst
doc/source/view_list.rst
doc/source/wrappers.rst
doc/source/zuul.rst
etc/jenkins_jobs.ini-sample
jenkins_jobs/__init__.py
jenkins_jobs/builder.py
jenkins_jobs/cache.py
jenkins_jobs/config.py
jenkins_jobs/constants.py
jenkins_jobs/errors.py
jenkins_jobs/formatter.py
jenkins_jobs/local_yaml.py
jenkins_jobs/parallel.py
jenkins_jobs/parser.py
jenkins_jobs/registry.py
jenkins_jobs/utils.py
jenkins_jobs/version.py
jenkins_jobs/xml_config.py
jenkins_jobs/cli/__init__.py
jenkins_jobs/cli/entry.py
jenkins_jobs/cli/parser.py
jenkins_jobs/cli/subcommand/__init__.py
jenkins_jobs/cli/subcommand/base.py
jenkins_jobs/cli/subcommand/delete.py
jenkins_jobs/cli/subcommand/delete_all.py
jenkins_jobs/cli/subcommand/test.py
jenkins_jobs/cli/subcommand/update.py
jenkins_jobs/modules/__init__.py
jenkins_jobs/modules/base.py
jenkins_jobs/modules/builders.py
jenkins_jobs/modules/general.py
jenkins_jobs/modules/helpers.py
jenkins_jobs/modules/hipchat_notif.py
jenkins_jobs/modules/hudson_model.py
jenkins_jobs/modules/metadata.py
jenkins_jobs/modules/notifications.py
jenkins_jobs/modules/parameters.py
jenkins_jobs/modules/project_externaljob.py
zerotk.jenkins_job_builder.egg-info/PKG-INFO
zerotk.jenkins_job_builder.egg-info/SOURCES.txt
zerotk.jenkins_job_builder.egg-info/dependency_links.txt
zerotk.jenkins_job_builder.egg-info/entry_points.txt
zerotk.jenkins_job_builder.egg-info/not-zip-safe
zerotk.jenkins_job_builder.egg-info/pbr.json
zerotk.jenkins_job_builder.egg-info/requires.txt
zerotk.jenkins_job_builder.egg-info/top_level.txt