Metadata-Version: 1.1
Name: zerotk.jenkins-job-builder
Version: 2.0.0.0b2
Summary: Manage Jenkins jobs with YAML
Home-page: http://docs.openstack.org/infra/system-config/jjb.html
Author: OpenStack Infrastructure Team
Author-email: openstack-infra@lists.openstack.org
License: Apache License, Version 2.0
Platform: UNKNOWN
Classifier: Topic :: Utilities
Classifier: Environment :: Console
Classifier: Intended Audience :: Developers
Classifier: Intended Audience :: Information Technology
Classifier: Intended Audience :: System Administrators
Classifier: License :: OSI Approved :: Apache Software License
Classifier: Operating System :: OS Independent
Classifier: Programming Language :: Python
Classifier: Programming Language :: Python :: 2
Classifier: Programming Language :: Python :: 2.7
Classifier: Programming Language :: Python :: 3
Classifier: Programming Language :: Python :: 3.4
